src/__init__.py
src/config_loader.py
src/graphiti_mcp_server.py
src/oauth_wrapper.py
src/ollama_client.py
src/config/__init__.py
src/config/database_config.py
src/config/embedder_config.py
src/config/llm_config.py
src/config/server_config.py
src/initialization/__init__.py
src/initialization/graphiti_client.py
src/initialization/server_setup.py
src/models/__init__.py
src/models/entity_types.py
src/models/response_models.py
src/tools/__init__.py
src/tools/management_tools.py
src/tools/memory_tools.py
src/tools/search_tools.py
src/utils/__init__.py
src/utils/auth_utils.py
src/utils/formatting_utils.py
src/utils/initialization_state.py
src/utils/ollama_health_validator.py
src/utils/ollama_response_converter.py
src/utils/queue_utils.py
montesmakes_graphiti_memory-0.4.3.dist-info/METADATA
montesmakes_graphiti_memory-0.4.3.dist-info/WHEEL
montesmakes_graphiti_memory-0.4.3.dist-info/entry_points.txt
montesmakes_graphiti_memory-0.4.3.dist-info/licenses/LICENSE
montesmakes_graphiti_memory-0.4.3.dist-info/RECORD
