Metadata-Version: 2.4
Name: montesmakes.graphiti-memory
Version: 0.4.3
Summary: Graphiti MCP Server - Memory service for AI agents built on temporal knowledge graphs
Project-URL: Homepage, https://github.com/mandelbro/graphiti-memory
Project-URL: Documentation, https://github.com/mandelbro/graphiti-memory/blob/main/README.md
Project-URL: Repository, https://github.com/mandelbro/graphiti-memory.git
Project-URL: Issues, https://github.com/mandelbro/graphiti-memory/issues
Author-email: Made byMontes <chris@montesmakes.co>
License: Apache-2.0
License-File: LICENSE
Keywords: agents,ai,graphiti,knowledge-graph,mcp,memory
Classifier: Development Status :: 4 - Beta
Classifier: Intended Audience :: Developers
Classifier: License :: OSI Approved :: Apache Software License
Classifier: Programming Language :: Python :: 3
Classifier: Programming Language :: Python :: 3.10
Classifier: Programming Language :: Python :: 3.11
Classifier: Programming Language :: Python :: 3.12
Classifier: Programming Language :: Python :: 3.13
Classifier: Topic :: Scientific/Engineering :: Artificial Intelligence
Classifier: Topic :: Software Development :: Libraries :: Python Modules
Requires-Python: <4,>=3.10
Requires-Dist: aiohttp>=3.12.15
Requires-Dist: azure-identity>=1.24.0
Requires-Dist: fastapi>=0.116.1
Requires-Dist: graphiti-core>=0.18.5
Requires-Dist: httpx>=0.28.1
Requires-Dist: mcp>=1.12.4
Requires-Dist: openai>=1.99.9
Requires-Dist: python-dotenv>=1.1.1
Requires-Dist: pyyaml>=6.0.1
Requires-Dist: starlette>=0.47.2
Requires-Dist: uvicorn>=0.35.0
Provides-Extra: dev
Requires-Dist: black>=25.1.0; extra == 'dev'
Requires-Dist: mypy>=1.17.1; extra == 'dev'
Requires-Dist: pyright>=1.1.0; extra == 'dev'
Requires-Dist: pytest-asyncio>=1.1.0; extra == 'dev'
Requires-Dist: pytest-cov>=6.2.1; extra == 'dev'
Requires-Dist: pytest-mock>=3.14.0; extra == 'dev'
Requires-Dist: pytest>=8.4.1; extra == 'dev'
Requires-Dist: ruff>=0.12.8; extra == 'dev'
Requires-Dist: twine>=6.1.0; extra == 'dev'
